noice/__init__.py
noice-0.1.6.dist-info/LICENSE
noice-0.1.6.dist-info/WHEEL
noice-0.1.6.dist-info/METADATA
noice-0.1.6.dist-info/RECORD
