Metadata-Version: 2.1
Name: noice
Version: 0.1.6
Summary: Data Engineering tools.
Home-page: https://github.com/Mashey/noice
License: MIT
Author: Jordan
Author-email: jordan@mashey.com
Requires-Python: >=3.9,<4.0
Classifier: License :: OSI Approved :: MIT License
Classifier: Programming Language :: Python :: 3
Classifier: Programming Language :: Python :: 3.9
Requires-Dist: Jinja2 (>=3.0.1,<4.0.0)
Requires-Dist: click (>=8.0.1,<9.0.0)
Requires-Dist: cookiecutter (>=1.7.3,<2.0.0)
Requires-Dist: python-fire (>=0.1.0,<0.2.0)
Requires-Dist: requests (>=2.25.1,<3.0.0)
Requires-Dist: rich (>=10.2.2,<11.0.0)
Requires-Dist: sendgrid (>=6.7.0,<7.0.0)
Project-URL: Repository, https://github.com/Mashey/noice
